aliyunsdkslb/__init__.py
aliyunsdkslb/endpoint.py
aliyunsdkslb/request/__init__.py
aliyunsdkslb/request/v20140515/AddAccessControlListEntryRequest.py
aliyunsdkslb/request/v20140515/AddBackendServersRequest.py
aliyunsdkslb/request/v20140515/AddListenerWhiteListItemRequest.py
aliyunsdkslb/request/v20140515/AddTagsRequest.py
aliyunsdkslb/request/v20140515/AddVServerGroupBackendServersRequest.py
aliyunsdkslb/request/v20140515/CreateAccessControlListRequest.py
aliyunsdkslb/request/v20140515/CreateDomainExtensionRequest.py
aliyunsdkslb/request/v20140515/CreateLoadBalancerHTTPListenerRequest.py
aliyunsdkslb/request/v20140515/CreateLoadBalancerHTTPSListenerRequest.py
aliyunsdkslb/request/v20140515/CreateLoadBalancerRequest.py
aliyunsdkslb/request/v20140515/CreateLoadBalancerTCPListenerRequest.py
aliyunsdkslb/request/v20140515/CreateLoadBalancerUDPListenerRequest.py
aliyunsdkslb/request/v20140515/CreateMasterSlaveServerGroupRequest.py
aliyunsdkslb/request/v20140515/CreateRulesRequest.py
aliyunsdkslb/request/v20140515/CreateTLSCipherPolicyRequest.py
aliyunsdkslb/request/v20140515/CreateVServerGroupRequest.py
aliyunsdkslb/request/v20140515/DeleteAccessControlListRequest.py
aliyunsdkslb/request/v20140515/DeleteAccessLogsDownloadAttributeRequest.py
aliyunsdkslb/request/v20140515/DeleteCACertificateRequest.py
aliyunsdkslb/request/v20140515/DeleteDomainExtensionRequest.py
aliyunsdkslb/request/v20140515/DeleteLoadBalancerListenerRequest.py
aliyunsdkslb/request/v20140515/DeleteLoadBalancerRequest.py
aliyunsdkslb/request/v20140515/DeleteMasterSlaveServerGroupRequest.py
aliyunsdkslb/request/v20140515/DeleteRulesRequest.py
aliyunsdkslb/request/v20140515/DeleteServerCertificateRequest.py
aliyunsdkslb/request/v20140515/DeleteTLSCipherPolicyRequest.py
aliyunsdkslb/request/v20140515/DeleteVServerGroupRequest.py
aliyunsdkslb/request/v20140515/DescribeAccessControlListAttributeRequest.py
aliyunsdkslb/request/v20140515/DescribeAccessControlListsRequest.py
aliyun_python_sdk_slb-3.3.22.dist-info/LICENSE
aliyun_python_sdk_slb-3.3.22.dist-info/METADATA
aliyun_python_sdk_slb-3.3.22.dist-info/WHEEL
aliyun_python_sdk_slb-3.3.22.dist-info/top_level.txt
aliyun_python_sdk_slb-3.3.22.dist-info/RECORD
